landborn/__init__.py
landborn/barplot.py
landborn/colormap.py
landborn/config.py
landborn/functions.py
landborn/gradient.py
landborn/heatmap.py
landborn/jointplot.py
landborn/lineplot.py
landborn/scatterplot.py
landborn/swarmplot3.py
landborn-0.2.7.dist-info/LICENSE
landborn-0.2.7.dist-info/METADATA
landborn-0.2.7.dist-info/WHEEL
landborn-0.2.7.dist-info/top_level.txt
landborn-0.2.7.dist-info/RECORD
