Metadata-Version: 2.1
Name: landborn
Version: 0.2.7
Summary: Landborn Visualization Library
Author: Molly Nelson
Author-email: mollyynelson@gmail.com
License: MIT
License-File: LICENSE
Requires-Dist: pandas
Requires-Dist: numpy
Requires-Dist: matplotlib
Requires-Dist: plotly
